bottle_openapi_3/__init__.py
bottle_openapi_3/vendor/swagger-ui-3.38.0-dist/favicon-16x16.png
bottle_openapi_3/vendor/swagger-ui-3.38.0-dist/favicon-32x32.png
bottle_openapi_3/vendor/swagger-ui-3.38.0-dist/index.html
bottle_openapi_3/vendor/swagger-ui-3.38.0-dist/index.html.st
bottle_openapi_3/vendor/swagger-ui-3.38.0-dist/oauth2-redirect.html
bottle_openapi_3/vendor/swagger-ui-3.38.0-dist/swagger-ui-bundle.js
bottle_openapi_3/vendor/swagger-ui-3.38.0-dist/swagger-ui-es-bundle-core.js
bottle_openapi_3/vendor/swagger-ui-3.38.0-dist/swagger-ui-es-bundle.js
bottle_openapi_3/vendor/swagger-ui-3.38.0-dist/swagger-ui-standalone-preset.js
bottle_openapi_3/vendor/swagger-ui-3.38.0-dist/swagger-ui.css
bottle_openapi_3/vendor/swagger-ui-3.38.0-dist/swagger-ui.js
bottle_openapi_3-0.1.2.dist-info/LICENSE
bottle_openapi_3-0.1.2.dist-info/METADATA
bottle_openapi_3-0.1.2.dist-info/WHEEL
bottle_openapi_3-0.1.2.dist-info/top_level.txt
bottle_openapi_3-0.1.2.dist-info/RECORD
