Metadata-Version: 2.1
Name: bottle-openapi-3
Version: 0.1.2
Summary: OpenAPI Integration for Bottle
Home-page: https://github.com/cope-systems/bottle-openapi-3
Author: Robert Cope
Author-email: robert@copesystems.com
License: MIT
Download-URL: https://github.com/cope-systems/bottle-openapi-3/archive/v0.1.2.tar.gz
Platform: any
Classifier: Development Status :: 3 - Alpha
Classifier: Environment :: Web Environment
Classifier: Environment :: Plugins
Classifier: Framework :: Bottle
Classifier: Intended Audience :: Developers
Classifier: License :: OSI Approved :: MIT License
Classifier: Operating System :: OS Independent
Classifier: Programming Language :: Python
Classifier: Programming Language :: Python :: 3.5
Classifier: Programming Language :: Python :: 3.6
Classifier: Programming Language :: Python :: 3.7
Classifier: Programming Language :: Python :: 3.8
Classifier: Programming Language :: Python :: 3.9
Classifier: Topic :: Internet :: WWW/HTTP :: Dynamic Content
Classifier: Topic :: Software Development :: Libraries :: Python Modules
Requires-Dist: bottle (>=0.12.0)
Requires-Dist: openapi-core (~=0.13.4)
Requires-Dist: openapi-spec-validator (~=0.2.9)
Requires-Dist: six
